{
  "$schema": "https://static.modelcontextprotocol.io/schemas/2025-12-11/server.schema.json",
  "name": "io.github.janmalmstrom/lupaph-mcp",
  "description": "Philippine property listings, transfer costs, and real estate legal info via lupaph.com.",
  "repository": {
    "url": "https://github.com/janmalmstrom/lupaph-mcp",
    "source": "github"
  },
  "version": "1.0.1",
  "packages": [
    {
      "registryType": "npm",
      "identifier": "lupaph-mcp",
      "version": "1.0.1",
      "transport": {
        "type": "stdio"
      }
    }
  ]
}
